LICENSE.txt
MANIFEST.in
README.md
VERSION
requirements-test.txt
setup.py
assetid/__init__.py
assetid/urn.py
assetid.egg-info/PKG-INFO
assetid.egg-info/SOURCES.txt
assetid.egg-info/dependency_links.txt
assetid.egg-info/top_level.txt
assetid/tests/__init__.py
assetid/tests/test_urn.py