Metadata-Version: 1.1
Name: assetid
Version: 1.0.0
Summary: An ocean data asset ID parser developed and used by Axiom Data Science
Home-page: https://github.com/axiom-data-science/assetid
Author: Kyle Wilcox
Author-email: kyle@axiomdatascience.com
License: MIT
Platform: UNKNOWN
Classifier: Development Status :: 3 - Alpha
Classifier: Intended Audience :: Developers
Classifier: Intended Audience :: Science/Research
Classifier: License :: OSI Approved :: MIT License
Classifier: Operating System :: POSIX :: Linux
Classifier: Programming Language :: Python
Classifier: Topic :: Scientific/Engineering
